LiaoXuefengJavascriptPythonGitJiaocheng/README.md
LiaoXuefengJavascriptPythonGitJiaocheng/__init__.py
LiaoXuefengJavascriptPythonGitJiaocheng/__main__.py
LiaoXuefengJavascriptPythonGitJiaocheng/file.epub
LiaoXuefengJavascriptPythonGitJiaocheng/index.html
LiaoXuefengJavascriptPythonGitJiaocheng/css/__init__.py
LiaoXuefengJavascriptPythonGitJiaocheng/css/annotations.css
LiaoXuefengJavascriptPythonGitJiaocheng/css/main.css
LiaoXuefengJavascriptPythonGitJiaocheng/css/normalize.css
LiaoXuefengJavascriptPythonGitJiaocheng/css/popup.css
LiaoXuefengJavascriptPythonGitJiaocheng/font/__init__.py
LiaoXuefengJavascriptPythonGitJiaocheng/font/fontello.eot
LiaoXuefengJavascriptPythonGitJiaocheng/font/fontello.svg
LiaoXuefengJavascriptPythonGitJiaocheng/font/fontello.ttf
LiaoXuefengJavascriptPythonGitJiaocheng/font/fontello.woff
LiaoXuefengJavascriptPythonGitJiaocheng/img/__init__.py
LiaoXuefengJavascriptPythonGitJiaocheng/img/annotator-glyph-sprite.png
LiaoXuefengJavascriptPythonGitJiaocheng/img/annotator-icon-sprite.png
LiaoXuefengJavascriptPythonGitJiaocheng/img/apple-touch-icon.png
LiaoXuefengJavascriptPythonGitJiaocheng/img/cancelfullscreen.png
LiaoXuefengJavascriptPythonGitJiaocheng/img/close.png
LiaoXuefengJavascriptPythonGitJiaocheng/img/fullscreen.png
LiaoXuefengJavascriptPythonGitJiaocheng/img/loader.gif
LiaoXuefengJavascriptPythonGitJiaocheng/img/menu-icon.png
LiaoXuefengJavascriptPythonGitJiaocheng/img/save.png
LiaoXuefengJavascriptPythonGitJiaocheng/img/saved.png
LiaoXuefengJavascriptPythonGitJiaocheng/img/settings-s.png
LiaoXuefengJavascriptPythonGitJiaocheng/img/settings.png
LiaoXuefengJavascriptPythonGitJiaocheng/img/star.png
LiaoXuefengJavascriptPythonGitJiaocheng/js/__init__.py
LiaoXuefengJavascriptPythonGitJiaocheng/js/epub.js
LiaoXuefengJavascriptPythonGitJiaocheng/js/epub.min.js
LiaoXuefengJavascriptPythonGitJiaocheng/js/epub.min.map
LiaoXuefengJavascriptPythonGitJiaocheng/js/hooks.min.js
LiaoXuefengJavascriptPythonGitJiaocheng/js/hooks.min.map
liao_xuefeng_javascript_python_git_jiaocheng-2024.3.2.0.dist-info/METADATA
liao_xuefeng_javascript_python_git_jiaocheng-2024.3.2.0.dist-info/WHEEL
liao_xuefeng_javascript_python_git_jiaocheng-2024.3.2.0.dist-info/entry_points.txt
liao_xuefeng_javascript_python_git_jiaocheng-2024.3.2.0.dist-info/top_level.txt
liao_xuefeng_javascript_python_git_jiaocheng-2024.3.2.0.dist-info/RECORD
